decpys/__init__.py
decpys/_config.py
decpys/cascade.py
decpys/gui.py
decpys/types.py
decpys/widgets.py
decpys-0.1.0.dist-info/LICENSE.txt
decpys-0.1.0.dist-info/METADATA
decpys-0.1.0.dist-info/WHEEL
decpys-0.1.0.dist-info/top_level.txt
decpys-0.1.0.dist-info/RECORD
