Metadata-Version: 2.1
Name: decpys
Version: 0.1.0
Summary: A Qt library extension for building declarative programming -style UIs completely within python.
Home-page: https://github.com/mbenzreba.decpys
Author: Mohamed Benzreba
Author-email: mbenzreba05@gmail.com
License: GPL-2.0-or-later
Project-URL: Bug Tracker, https://github.com/mbenzreba/decpys/issues
Platform: UNKNOWN
Classifier: Development Status :: 3 - Alpha
Classifier: Intended Audience :: Developers
Classifier: License :: OSI Approved :: GNU General Public License v2 or later (GPLv2+)
Classifier: Operating System :: OS Independent
Classifier: Programming Language :: Python :: 3.9
Requires-Python: >=3.5
License-File: LICENSE.txt
Requires-Dist: PySide6 (==6.2.3)
